latform/__init__.py
latform/__main__.py
latform/_attrs.py
latform/_version.py
latform/attrs.py
latform/comments.py
latform/const.py
latform/dump.py
latform/exceptions.py
latform/funcs.py
latform/graph.py
latform/lint.py
latform/location.py
latform/main.py
latform/output.py
latform/parser.py
latform/species.py
latform/statements.py
latform/token.py
latform/tokenizer.py
latform/types.py
latform/util.py
latform/tests/__init__.py
latform/tests/conftest.py
latform/tests/test_entrypoint.py
latform/tests/test_output.py
latform/tests/test_parse.py
latform/tests/test_species.py
latform/tests/test_tao_roundtrip.py
latform/tests/files/__init__.py
latform/tests/files/fodo.bmad
latform/tests/files/parse_test.bmad
latform/tests/files/sub_dir/__init__.py
latform/tests/files/sub_dir/sub.bmad
latform/tests/files/sub_dir/sub2_dir/__init__.py
latform/tests/files/sub_dir/sub2_dir/sub2.bmad
latform-0.1.3.dist-info/licenses/LICENSE
latform-0.1.3.dist-info/METADATA
latform-0.1.3.dist-info/WHEEL
latform-0.1.3.dist-info/entry_points.txt
latform-0.1.3.dist-info/top_level.txt
latform-0.1.3.dist-info/RECORD
