Metadata-Version: 2.4
Name: latform
Version: 0.1.3
Summary: Bmad lattice parser/formatter tool
Author-email: Ken Lauer <152229072+ken-lauer@users.noreply.github.com>
License: Copyright 2025 Ken Lauer
Classifier: Development Status :: 4 - Beta
Classifier: Natural Language :: English
Classifier: Programming Language :: Python :: 3
Classifier: Topic :: Scientific/Engineering
Requires-Python: >=3.10
License-File: LICENSE
Requires-Dist: rich
Requires-Dist: typing_extensions; python_version < "3.11"
Provides-Extra: test
Requires-Dist: pytest; extra == "test"
Requires-Dist: pytest-cov; extra == "test"
Requires-Dist: pytest-mock; extra == "test"
Provides-Extra: doc
Requires-Dist: mkdocs; extra == "doc"
Requires-Dist: mkdocstrings; extra == "doc"
Requires-Dist: mkdocstrings-python; extra == "doc"
Dynamic: license-file
